gs_manager
