Metadata-Version: 1.1
Name: game-server-manager
Version: 0.1.1
Summary: Command to manage and control various types of game servers.
Home-page: https://github.com/AngellusMortis/game_server_manager
Author: Christopher Bailey
Author-email: cbailey@mort.is
License: MIT license
Keywords: game_server_manager
Platform: UNKNOWN
Classifier: Development Status :: 4 - Beta
Classifier: Intended Audience :: Developers
Classifier: Intended Audience :: System Administrators
Classifier: License :: OSI Approved :: MIT License
Classifier: Natural Language :: English
Classifier: Programming Language :: Python :: 2
Classifier: Programming Language :: Python :: 2.7
Classifier: Programming Language :: Python :: 3
Classifier: Programming Language :: Python :: 3.4
Classifier: Programming Language :: Python :: 3.5
Classifier: Programming Language :: Python :: 3.6
